setup.cfg
setup.py
lexrankr/__init__.py
lexrankr/lexrankr.py
lexrankr.egg-info/PKG-INFO
lexrankr.egg-info/SOURCES.txt
lexrankr.egg-info/dependency_links.txt
lexrankr.egg-info/requires.txt
lexrankr.egg-info/top_level.txt
tests/__init__.py
tests/test.py