Metadata-Version: 1.0
Name: lexrankr
Version: 0.1.5
Summary: LexRank for Korean
Home-page: https://github.com/theeluwin/lexrankr
Author: Jamie Seol
Author-email: theeluwin@gmail.com
License: MIT
Platform: UNKNOWN
